plone.alterego-2.0.2-py3.13-nspkg.pth
plone/alterego/__init__.py
plone/alterego/alterego.txt
plone/alterego/dynamic.py
plone/alterego/interfaces.py
plone/alterego/tests.py
plone_alterego-2.0.2.dist-info/METADATA
plone_alterego-2.0.2.dist-info/WHEEL
plone_alterego-2.0.2.dist-info/namespace_packages.txt
plone_alterego-2.0.2.dist-info/top_level.txt
plone_alterego-2.0.2.dist-info/RECORD
